opensesame_plugins/parallel_port_trigger/__init__.py
opensesame_plugins/parallel_port_trigger/parallel_port_trigger_init/__init__.py
opensesame_plugins/parallel_port_trigger/parallel_port_trigger_init/inpout32.dll
opensesame_plugins/parallel_port_trigger/parallel_port_trigger_init/inpoutx64.dll
opensesame_plugins/parallel_port_trigger/parallel_port_trigger_init/parallel_port_trigger_init.png
opensesame_plugins/parallel_port_trigger/parallel_port_trigger_init/parallel_port_trigger_init.py
opensesame_plugins/parallel_port_trigger/parallel_port_trigger_init/parallel_port_trigger_init_large.png
opensesame_plugins/parallel_port_trigger/parallel_port_trigger_send/__init__.py
opensesame_plugins/parallel_port_trigger/parallel_port_trigger_send/parallel_port_trigger_send.png
opensesame_plugins/parallel_port_trigger/parallel_port_trigger_send/parallel_port_trigger_send.py
opensesame_plugins/parallel_port_trigger/parallel_port_trigger_send/parallel_port_trigger_send_large.png
opensesame_plugin_parallel_port_trigger-4.3.0.dist-info/COPYING
opensesame_plugin_parallel_port_trigger-4.3.0.dist-info/LICENSE.md
opensesame_plugin_parallel_port_trigger-4.3.0.dist-info/METADATA
opensesame_plugin_parallel_port_trigger-4.3.0.dist-info/WHEEL
opensesame_plugin_parallel_port_trigger-4.3.0.dist-info/RECORD
