Metadata-Version: 2.3
Name: opensesame-plugin-parallel_port_trigger
Version: 4.3.0
Summary: An OpenSesame Plug-in for sending stimulus synchronization triggers through the parallel port to data acquisition systems
License: LICENSE.md
Author: Bob Rosbag
Author-email: debian@bobrosbag.nl
Requires-Python: >=3.7
Classifier: License :: Other/Proprietary License
Classifier: Programming Language :: Python :: 3
Classifier: Programming Language :: Python :: 3.7
Classifier: Programming Language :: Python :: 3.8
Classifier: Programming Language :: Python :: 3.9
Classifier: Programming Language :: Python :: 3.10
Classifier: Programming Language :: Python :: 3.11
Classifier: Programming Language :: Python :: 3.12
Classifier: Programming Language :: Python :: 3.13
Requires-Dist: pyparallel (>=0.2.2) ; sys_platform == "linux"
Project-URL: Homepage, https://github.com/dev-jam/opensesame-plugin-parallel_port_trigger
Project-URL: Repository, https://github.com/dev-jam/opensesame-plugin-parallel_port_trigger
